rexapi/__init__.py
rexapi/api.py
rexapi-0.0.1.dist-info/LICENSE
rexapi-0.0.1.dist-info/METADATA
rexapi-0.0.1.dist-info/WHEEL
rexapi-0.0.1.dist-info/top_level.txt
rexapi-0.0.1.dist-info/RECORD
