Metadata-Version: 2.1
Name: rexapi
Version: 0.0.1
Summary: An API wrapper for the CookieBot API
Author: Jinx
License: MIT
Project-URL: GitHub, https://github.com/Jinxex/rex-api
Project-URL: Documentation, https://rexapi.readthedocs.io/en/latest/
Keywords: rexapi,rex,api
Classifier: Development Status :: 4 - Beta
Classifier: License :: OSI Approved :: MIT License
Classifier: Intended Audience :: Developers
Classifier: Operating System :: OS Independent
Classifier: Programming Language :: Python :: 3.9
Classifier: Programming Language :: Python :: 3.10
Classifier: Programming Language :: Python :: 3.11
Classifier: Programming Language :: Python :: 3.12
Requires-Python: >=3.9
License-File: LICENSE
Requires-Dist: aiohttp
